{
    "users": [
        {
            "id": 1,
            "fname": "Mark ",
            "lname": "Zuckerberg",
            "email": "mark@gmail.com",
            "password": "12345678",
            "password_confirmation": "12345678",
            "phone": "0954721021",
            "address": "USA"
        },
        {
            "id": 2,
            "fname": "Elon ",
            "lname": "Musk",
            "email": "elon@gmail.com",
            "password": "12345678",
            "password_confirmation": "12345678",
            "phone": "0254052574",
            "address": "USA"
        },
        {
            "id": 3,
            "fname": "Bill",
            "lname": "Gate",
            "email": "bill@gmail.com",
            "password": "12345678",
            "password_confirmation": "12345678",
            "phone": "4689656797",
            "address": "USA"
        },
        {
            "id": 4,
            "fname": "Jeff",
            "lname": "Beszos",
            "email": "jeff@gmail.com",
            "password": "12345678",
            "password_confirmation": "12345678",
            "phone": "0467979746",
            "address": "USA"
        },
        {
            "id": 5,
            "fname": "Jack",
            "lname": "ma",
            "email": "jack@gmail.com",
            "password": "12345678",
            "password_confirmation": "12345678",
            "phone": "7878787879",
            "address": "china"
        }
    ],
    "elder": [
        {
            "id": 1,
            "name": "Nergigante",
            "location": "Nergigante เป็นมังกรที่มีรูปร่างหน้าตาแข็งแรง มันถูกปกคลุมไปด้วยหนามแหลมซึ่งจะงอกขึ้นมาใหม่อย่างต่อเนื่องเมื่อหักออก มีเขาขนาดใหญ่สองเขาคล้ายวัว หนังของสัตว์ประหลาดส่วนใหญ่เป็นสีดำ เน้นสีม่วงและสีส้ม",
            "imageUrl": "https://i.ytimg.com/vi/L9cWR-urZH0/maxresdefault.jpg"
        },
        {
            "id": 2,
            "name": "Teostra",
            "location": "Teostra เป็นมังกรตัวใหญ่ที่มีรูปร่างเหมือนลีโอนีนและมีสีแดงเพลิง เขามีแผงคอขนาดใหญ่ เขี้ยวขนาดใหญ่ และมีเขาคู่หนึ่งที่โค้งไปด้านหลัง ปีกของเขาปกคลุมไปด้วยขน และปลายหางของมันก็จะเต็มไปด้วยขน",
            "imageUrl": "https://assetsio.reedpopcdn.com/monster-hunter-world-teostra-title.png?width=1200&height=1200&fit=bounds&quality=70&format=jpg&auto=webp"
        },
        {
            "id": 3,
            "name": "Lunastra",
            "location": "Lunastra เป็นมังกรที่มีคุณสมบัติลีโอนีนและมีสีที่เย็นตา เธอมีแผงคอที่โดดเด่น เขี้ยวขนาดใหญ่ และมีหงอนที่โดดเด่นซึ่งมีลักษณะคล้ายมงกุฎ ปีกของเธอปกคลุมไปด้วยขน",
            "imageUrl": "https://www.rgj.com/gcdn/-mm-/9a10d18443197ab9a2a837953a60ea6375b5467c/c=4-0-1916-1080/local/-/media/2018/05/31/Reno/RGJ/636633943279914529-Lunastra-with-Teostra.jpg"
        },
        {
            "id": 5,
            "name": "Vaal Hazak",
            "location": "Vaal Hazak เป็นมังกรที่เรียวยาวและมีลักษณะทางกายภาพที่เป็นเอกลักษณ์หลายประการ ตัวของมันถูกปกคลุมไปด้วยเกล็ดสีเงินซึ่งถูกบดบังด้วยผ้าคลุมสีแดงเนื้อที่ปกคลุมเกือบทั้งตัว มันมีกรามล่างคู่ที่โดดเด่น โดยแต่ละอันมีเขี้ยวแหลมคมยาวมากคล้ายกับของปลาทะเลน้ำลึก มีจุดสีเหลืองสดใสสองจุดที่ด้านข้างของหัวและมีตาสีแดงเล็กๆ สองดวง นิ้วเท้าและปลายปีกประดับด้วยกรงเล็บรูปเคียว",
            "imageUrl": "https://i.ytimg.com/vi/9M8G0-Mwf6Y/maxresdefault.jpg"
        },
        {
            "id": 5,
            "name": "Kushala Daora",
            "location": "Kushala Daora เป็นมังกรที่มีผิวหนังเป็นโลหะ ปีกขนาดใหญ่เชื่อมต่อกันที่โคนหาง ทำให้ดูใหญ่ขึ้นตามสัดส่วนของลำตัว เขาโค้งไปด้านหลัง 2 เขาวางอยู่บนหัวทั้งสองข้าง ผสมผสานกับหนามแหลมที่อยู่ด้านหลัง มีลมพัดให้เห็นทั่วตัว กูชาลามีจมูกสีแดงเล็กน้อย อาจเป็นสัญญาณของสนิม",
            "imageUrl": "https://assetsio.reedpopcdn.com/monster-hunter-world-kushala-title.png?width=1200&height=1200&fit=bounds&quality=70&format=jpg&auto=webp"
        },
        {
            "id": 6,
            "name": "Kirin",
            "location": "Kirin มีลักษณะคล้ายยูนิคอร์น แต่เมื่อมองใกล้ ๆ ก็พบว่ามีใบหน้าเหมือนสิงโตและมีเกล็ดปกคลุมอยู่ แทนที่จะเป็นเสื้อคลุม คิรินมีแผงคอที่ทำจากขนสัตว์และมีปลายหางเป็นพวง ขนเป็นกระจุกพาดผ่านไหล่และเหนือกีบ คิรินมีแถบสีดำคล้ายเครื่องหมายตามด้านข้างและขา สัตว์ร้ายมีดวงตาสีแดงเข้ม แผงคอและผมสีขาวสง่าของมันยืนตรงปลายราวกับมีประจุไฟฟ้าสถิต",
            "imageUrl": "https://www.rgj.com/gcdn/-mm-/9a10d18443197ab9a2a837953a60ea6375b5467c/c=4-0-1916-1080/local/-/media/2018/06/08/Reno/RGJ/636640660611065851-MHW-Arch-Tempered-Kirin.jpg"
        },
        {
            "id": 7,
            "name": "Xeno'jiiva",
            "location": "Xeno'jiiva เป็นมังกรตัวใหญ่ที่มีรูปร่างเหมือนสัตว์จากนอกโลก มีตาสองข้างและอวัยวะรับความรู้สึกสีส้มหกอันทอดยาวไปตามความยาวของเขา ส่วนต่างๆ ของร่างกายเรืองแสงเป็นสีน้ำเงิน ทำให้ผิวดูเป็นผลึกและโปร่งแสง ปีกของมันหลุดลุ่ยที่ขอบเยื่อหุ้มและมีสีเทาอมฟ้า เมื่อโกรธ เนื้อตัวจะเรืองแสงเป็นสีแดงและสีส้ม",
            "imageUrl": "https://i.ytimg.com/vi/uE5aWKOVJm4/maxresdefault.jpg"
        },
        {
            "id": 8,
            "name": "Zorah Magdaros",
            "location": "Zorah Magdaros เป็นมังกรกึ่งน้ำขนาดมหึมาที่ปกคลุมไปด้วยหนังหิน มีลักษณะคล้ายเต่า มีเปลือกเป็นภูเขาบนหลังซึ่งสามารถล่าถอยลงไปได้ขณะเดินทั้งสี่ข้าง และมีปากจะงอย ไฟ ควัน และลาวาแผ่ออกมาจากเปลือกของสิ่งมีชีวิตอย่างต่อเนื่อง ทำให้มันคล้ายกับภูเขาไฟที่กำลังเดินอยู่มากกว่าสิ่งมีชีวิตทั่วไป",
            "imageUrl": "https://pbs.twimg.com/media/Dp0h0JkU8AE6RU6.jpg"
        }
    ]
}